crypto_toolkit/__init__.py
crypto_toolkit/crypto/__init__.py
crypto_toolkit/crypto/asymmetric/__init__.py
crypto_toolkit/crypto/asymmetric/rsa.py
crypto_toolkit/crypto/hashing/__init__.py
crypto_toolkit/crypto/hashing/argon2id.py
crypto_toolkit/crypto/hashing/bcrypt.py
crypto_toolkit/crypto/hashing/sha_hmac.py
crypto_toolkit/crypto/symmetric/__init__.py
crypto_toolkit/crypto/symmetric/aes.py
crypto_toolkit/exceptions/__init__.py
crypto_toolkit/exceptions/crypto_errors.py
crypto_toolkit/key_management/__init__.py
crypto_toolkit/key_management/asymmetric.py
crypto_toolkit/key_management/symmetric.py
crypto_toolkit/utils/__init__.py
crypto_toolkit/utils/kid.py
crypto_toolkit-0.1.1.dist-info/licenses/LICENSE
crypto_toolkit-0.1.1.dist-info/METADATA
crypto_toolkit-0.1.1.dist-info/WHEEL
crypto_toolkit-0.1.1.dist-info/top_level.txt
crypto_toolkit-0.1.1.dist-info/RECORD
